ipykernel_launcher.py
ipykernel/__init__.py
ipykernel/__main__.py
ipykernel/_eventloop_macos.py
ipykernel/_version.py
ipykernel/compiler.py
ipykernel/connect.py
ipykernel/control.py
ipykernel/datapub.py
ipykernel/debugger.py
ipykernel/displayhook.py
ipykernel/embed.py
ipykernel/eventloops.py
ipykernel/heartbeat.py
ipykernel/iostream.py
ipykernel/ipkernel.py
ipykernel/jsonutil.py
ipykernel/kernelapp.py
ipykernel/kernelbase.py
ipykernel/kernelspec.py
ipykernel/log.py
ipykernel/parentpoller.py
ipykernel/pickleutil.py
ipykernel/py.typed
ipykernel/serialize.py
ipykernel/trio_runner.py
ipykernel/zmqshell.py
ipykernel/comm/__init__.py
ipykernel/comm/comm.py
ipykernel/comm/manager.py
ipykernel/gui/__init__.py
ipykernel/gui/gtk3embed.py
ipykernel/gui/gtkembed.py
ipykernel/inprocess/__init__.py
ipykernel/inprocess/blocking.py
ipykernel/inprocess/channels.py
ipykernel/inprocess/client.py
ipykernel/inprocess/constants.py
ipykernel/inprocess/ipkernel.py
ipykernel/inprocess/manager.py
ipykernel/inprocess/socket.py
ipykernel/inprocess/tests/__init__.py
ipykernel/inprocess/tests/test_kernel.py
ipykernel/inprocess/tests/test_kernelmanager.py
ipykernel/pylab/__init__.py
ipykernel/pylab/backend_inline.py
ipykernel/pylab/config.py
ipykernel/resources/logo-32x32.png
ipykernel/resources/logo-64x64.png
ipykernel/tests/__init__.py
ipykernel/tests/_asyncio_utils.py
ipykernel/tests/conftest.py
ipykernel/tests/test_async.py
ipykernel/tests/test_connect.py
ipykernel/tests/test_debugger.py
ipykernel/tests/test_embed_kernel.py
ipykernel/tests/test_eventloop.py
ipykernel/tests/test_heartbeat.py
ipykernel/tests/test_io.py
ipykernel/tests/test_jsonutil.py
ipykernel/tests/test_kernel.py
ipykernel/tests/test_kernelspec.py
ipykernel/tests/test_message_spec.py
ipykernel/tests/test_pickleutil.py
ipykernel/tests/test_start_kernel.py
ipykernel/tests/test_zmq_shell.py
ipykernel/tests/utils.py
ipykernel-6.13.0.data/data/share/jupyter/kernels/python3/kernel.json
ipykernel-6.13.0.dist-info/COPYING.md
ipykernel-6.13.0.dist-info/METADATA
ipykernel-6.13.0.dist-info/WHEEL
ipykernel-6.13.0.dist-info/top_level.txt
ipykernel-6.13.0.dist-info/RECORD
