Metadata-Version: 2.1
Name: ipykernel
Version: 6.13.0
Summary: IPython Kernel for Jupyter
Home-page: https://ipython.org
Author: IPython Development Team
Author-email: ipython-dev@scipy.org
License: BSD
Project-URL: Documentation, https://ipython.readthedocs.io/
Project-URL: Funding, https://numfocus.org/
Project-URL: Source, https://github.com/ipython/ipykernel
Project-URL: Tracker, https://github.com/ipython/ipykernel/issues
Keywords: Interactive,Interpreter,Shell,Web
Platform: Linux
Platform: Mac OS X
Platform: Windows
Classifier: Intended Audience :: Developers
Classifier: Intended Audience :: System Administrators
Classifier: Intended Audience :: Science/Research
Classifier: License :: OSI Approved :: BSD License
Classifier: Programming Language :: Python
Classifier: Programming Language :: Python :: 3
Classifier: Programming Language :: Python :: 3.7
Classifier: Programming Language :: Python :: 3.8
Classifier: Programming Language :: Python :: 3.9
Classifier: Programming Language :: Python :: 3.10
Requires-Python: >=3.7
Provides-Extra: test
License-File: COPYING.md
